python_edubase_api/__init__.py
python_edubase_api-0.0.2.dist-info/LICENSE
python_edubase_api-0.0.2.dist-info/METADATA
python_edubase_api-0.0.2.dist-info/WHEEL
python_edubase_api-0.0.2.dist-info/top_level.txt
python_edubase_api-0.0.2.dist-info/RECORD
