Metadata-Version: 2.2
Name: python_edubase_api
Version: 0.0.2
Summary: Python 3 пакет для взаимодействия с edubase-api
Author-email: Semyon Terebenin <semenchik02@gmail.com>
License:                     GNU GENERAL PUBLIC LICENSE
Project-URL: Homepage, http://gitea.shgpi/aneri/python_edubase_api
Project-URL: Issues, http://gitea.shgpi/aneri/python_edubase_api/issues
Classifier: Programming Language :: Python :: 3
Classifier: Operating System :: OS Independent
Requires-Python: >=3.8
License-File: LICENSE
Requires-Dist: requests
